odoo/addons/fieldservice_vehicle/README.rst
odoo/addons/fieldservice_vehicle/__init__.py
odoo/addons/fieldservice_vehicle/__manifest__.py
odoo/addons/fieldservice_vehicle/models/__init__.py
odoo/addons/fieldservice_vehicle/models/fsm_route.py
odoo/addons/fieldservice_vehicle/models/fsm_vehicle.py
odoo/addons/fieldservice_vehicle/readme/CONFIGURE.rst
odoo/addons/fieldservice_vehicle/readme/CONTRIBUTORS.rst
odoo/addons/fieldservice_vehicle/readme/CREDITS.rst
odoo/addons/fieldservice_vehicle/readme/DESCRIPTION.rst
odoo/addons/fieldservice_vehicle/readme/INSTALL.rst
odoo/addons/fieldservice_vehicle/readme/ROADMAP.rst
odoo/addons/fieldservice_vehicle/readme/USAGE.rst
odoo/addons/fieldservice_vehicle/security/ir.model.access.csv
odoo/addons/fieldservice_vehicle/security/res_groups.xml
odoo/addons/fieldservice_vehicle/static/description/icon.png
odoo/addons/fieldservice_vehicle/static/description/index.html
odoo/addons/fieldservice_vehicle/views/fsm_route.xml
odoo/addons/fieldservice_vehicle/views/fsm_vehicle.xml
odoo/addons/fieldservice_vehicle/views/menu.xml
odoo11_addon_fieldservice_vehicle-11.0.0.1.0.dist-info/METADATA
odoo11_addon_fieldservice_vehicle-11.0.0.1.0.dist-info/RECORD
odoo11_addon_fieldservice_vehicle-11.0.0.1.0.dist-info/WHEEL
odoo11_addon_fieldservice_vehicle-11.0.0.1.0.dist-info/top_level.txt
